{
    "customers": [
        {
            "firstName": "Nihad",
            "lastName": "Samaha",
            "fullName": "Nihad Samaha",
            "language": "Arabic",
            "gender": "Female",
            "firstNameNative": "نيهاد",
            "lastNameNative": "سماحة",
            "fullNameNative": "نيهاد سماحة"
        },
        {
            "firstName": "Susan",
            "lastName": "Kemp",
            "fullName": "Susan Kemp",
            "language": "Afrikaans",
            "gender": "Female",
            "firstNameNative": "Susan",
            "lastNameNative": "Kemp",
            "fullNameNative": "Susan Kemp"
        },
        {
            "firstName": "Helena",
            "lastName": "Botha",
            "fullName": "Helena Botha",
            "language": "Afrikaans",
            "gender": "Female",
            "firstNameNative": "Helena",
            "lastNameNative": "Botha",
            "fullNameNative": "Helena Botha"
        },
        {
            "firstName": "Gentiana",
            "lastName": "Gjoka",
            "fullName": "Gentiana Gjoka",
            "language": "Albanian",
            "gender": "Female",
            "firstNameNative": "Gentiana",
            "lastNameNative": "Gjoka",
            "fullNameNative": "Gentiana Gjoka"
        },
        {
            "firstName": "Humayd",
            "lastName": "Wahdani",
            "fullName": "Humayd Wahdani",
            "language": "Arabic",
            "gender": "Male",
            "firstNameNative": "حميد",
            "lastNameNative": "وهداني",
            "fullNameNative": "حميد وهداني"
        },
        {
            "firstName": "Kemiliya",
            "lastName": "Hussien",
            "fullName": "Kemiliya Hussien",
            "language": "Amharic",
            "gender": "Female",
            "firstNameNative": "ከሚሊያ",
            "lastNameNative": "ሁሴን",
            "fullNameNative": "ከሚሊያ ሁሴን"
        },
        {
            "firstName": "Jannie",
            "lastName": "du Toit",
            "fullName": "Jannie du Toit",
            "language": "Afrikaans",
            "gender": "Male",
            "firstNameNative": "Jannie",
            "lastNameNative": "du Toit",
            "fullNameNative": "Jannie du Toit"
        },
        {
            "firstName": "Eden",
            "lastName": "Sisay",
            "fullName": "Eden Sisay",
            "language": "Amharic",
            "gender": "Female",
            "firstNameNative": "ኤደን",
            "lastNameNative": "ሲሳይ",
            "fullNameNative": "ኤደን ሲሳይ"
        },
        {
            "firstName": "Wilna",
            "lastName": "Rossouw",
            "fullName": "Wilna Rossouw",
            "language": "Afrikaans",
            "gender": "Female",
            "firstNameNative": "Wilna",
            "lastNameNative": "Rossouw",
            "fullNameNative": "Wilna Rossouw"
        },
        {
            "firstName": "Lulu",
            "lastName": "Kuzbari",
            "fullName": "Lulu Kuzbari",
            "language": "Arabic",
            "gender": "Female",
            "firstNameNative": "لولو",
            "lastNameNative": "كزبري",
            "fullNameNative": "لولو كزبري"
        },
        {
            "firstName": "Ismat",
            "lastName": "Shamoun",
            "fullName": "Ismat Shamoun",
            "language": "Arabic",
            "gender": "Female",
            "firstNameNative": "عصمت",
            "lastNameNative": "شمعون",
            "fullNameNative": "عصمت شمعون"
        },
        {
            "firstName": "Jakeem",
            "lastName": "Mustafa",
            "fullName": "Jakeem Mustafa",
            "language": "Arabic",
            "gender": "Male",
            "firstNameNative": "جاكيم",
            "lastNameNative": "مصطفى",
            "fullNameNative": "جاكيم مصطفى"
        },
        {
            "firstName": "Mukhtar",
            "lastName": "Sarraf",
            "fullName": "Mukhtar Sarraf",
            "language": "Arabic",
            "gender": "Male",
            "firstNameNative": "مختار",
            "lastNameNative": "سراف",
            "fullNameNative": "مختار سراف"
        },
        {
            "firstName": "Eba",
            "lastName": "Lencho",
            "fullName": "Eba Lencho",
            "language": "Amharic",
            "gender": "Male",
            "firstNameNative": "ኤባ",
            "lastNameNative": "ሌንጮ",
            "fullNameNative": "ኤባ ሌንጮ"
        },
        {
            "firstName": "Piet",
            "lastName": "Smit",
            "fullName": "Piet Smit",
            "language": "Afrikaans",
            "gender": "Male",
            "firstNameNative": "Piet",
            "lastNameNative": "Smit",
            "fullNameNative": "Piet Smit"
        },
        {
            "firstName": "Rajab",
            "lastName": "Quraishi",
            "fullName": "Rajab Quraishi",
            "language": "Arabic",
            "gender": "Male",
            "firstNameNative": "رجب",
            "lastNameNative": "قريشي",
            "fullNameNative": "رجب قريشي"
        },
        {
            "firstName": "Etleva",
            "lastName": "Hysa",
            "fullName": "Etleva Hysa",
            "language": "Albanian",
            "gender": "Female",
            "firstNameNative": "Etleva",
            "lastNameNative": "Hysa",
            "fullNameNative": "Etleva Hysa"
        },
        {
            "firstName": "Juan",
            "lastName": "le Roux",
            "fullName": "Jaun le Roux",
            "language": "Afrikaans",
            "gender": "Male",
            "firstNameNative": "Juan",
            "lastNameNative": "le Roux",
            "fullNameNative": "Jaun le Roux"
        },
        {
            "firstName": "Annemarie",
            "lastName": "de Kock",
            "fullName": "Annemarie de Kock",
            "language": "Afrikaans",
            "gender": "Female",
            "firstNameNative": "Annemarie",
            "lastNameNative": "de Kock",
            "fullNameNative": "Annemarie de Kock"
        },
        {
            "firstName": "Ruwaidah",
            "lastName": "Fakhoury",
            "fullName": "Ruwaidah Fakhoury",
            "language": "Arabic",
            "gender": "Female",
            "firstNameNative": "رويدة",
            "lastNameNative": "فاخوري",
            "fullNameNative": "رويدة فاخوري"
        },
        {
            "firstName": "Homsi",
            "lastName": "Boutros",
            "fullName": "Homsi Boutros",
            "language": "Arabic",
            "gender": "Male",
            "firstNameNative": "حمصي",
            "lastNameNative": "بطرس",
            "fullNameNative": "حمصي بطرس"
        },
        {
            "firstName": "Selam",
            "lastName": "Fekadu",
            "fullName": "Selam Fekadu",
            "language": "Amharic",
            "gender": "Female",
            "firstNameNative": "ሰላም",
            "lastNameNative": "ፈቃዱ",
            "fullNameNative": "ሰላም ፈቃዱ"
        },
        {
            "firstName": "Thaqib",
            "lastName": "Hakimi",
            "fullName": "Thaqib Hakimi",
            "language": "Arabic",
            "gender": "Male",
            "firstNameNative": "ثقيب",
            "lastNameNative": "حكيمي",
            "fullNameNative": "ثقيب حكيمي"
        },
        {
            "firstName": "Sonila",
            "lastName": "Rama",
            "fullName": "Sonila Rama",
            "language": "Albanian",
            "gender": "Female",
            "firstNameNative": "Sonila",
            "lastNameNative": "Rama",
            "fullNameNative": "Sonila Rama"
        },
        {
            "firstName": "Yvonne",
            "lastName": "Dippenaar",
            "fullName": "Yvonne Dippenaar",
            "language": "Afrikaans",
            "gender": "Female",
            "firstNameNative": "Yvonne",
            "lastNameNative": "Dippenaar",
            "fullNameNative": "Yvonne Dippenaar"
        },
        {
            "firstName": "Nabighah",
            "lastName": "Maarouf",
            "fullName": "Nabighah Maarouf",
            "language": "Arabic",
            "gender": "Male",
            "firstNameNative": "نابغة",
            "lastNameNative": "معروف",
            "fullNameNative": "نابغة معروف"
        },
        {
            "firstName": "Brunilda",
            "lastName": "Kola",
            "fullName": "Brunilda Kola",
            "language": "Albanian",
            "gender": "Female",
            "firstNameNative": "Brunilda",
            "lastNameNative": "Kola",
            "fullNameNative": "Brunilda Kola"
        },
        {
            "firstName": "Chris",
            "lastName": "Groenewald",
            "fullName": "Chris Groenewalt",
            "language": "Afrikaans",
            "gender": "Male",
            "firstNameNative": "Chris",
            "lastNameNative": "Groenewald",
            "fullNameNative": "Chris Groenewalt"
        },
        {
            "firstName": "Maha",
            "lastName": "Kabara",
            "fullName": "Maha Kabara",
            "language": "Arabic",
            "gender": "Female",
            "firstNameNative": "مهى",
            "lastNameNative": "كبارة",
            "fullNameNative": "مهى كبارة"
        },
        {
            "firstName": "Azeem",
            "lastName": "Ghanem",
            "fullName": "Azeem Ghanem",
            "language": "Arabic",
            "gender": "Male",
            "firstNameNative": "عظيم",
            "lastNameNative": "غانم",
            "fullNameNative": "عظيم غانم"
        },
        {
            "firstName": "Ajlal",
            "lastName": "Nueimat",
            "fullName": "Ajlal Nueimat",
            "language": "Arabic",
            "gender": "Female",
            "firstNameNative": "أجلال",
            "lastNameNative": "نعيمة",
            "fullNameNative": "أجلال نعيمة"
        },
        {
            "firstName": "Yohannes",
            "lastName": "Yared",
            "fullName": "Yohannes Yared",
            "language": "Amharic",
            "gender": "Male",
            "firstNameNative": "ዮሃንስ",
            "lastNameNative": "ያሬድ",
            "fullNameNative": "ዮሃንስ ያሬድ"
        },
        {
            "firstName": "Malika",
            "lastName": "Aswad",
            "fullName": "Malika Aswad",
            "language": "Arabic",
            "gender": "Female",
            "firstNameNative": "ملكة",
            "lastNameNative": "أسود",
            "fullNameNative": "ملكة أسود"
        },
        {
            "firstName": "Hasibah",
            "lastName": "Kassis",
            "fullName": "Hasibah Kassis",
            "language": "Arabic",
            "gender": "Female",
            "firstNameNative": "حسيبة",
            "lastNameNative": "قسيس",
            "fullNameNative": "حسيبة قسيس"
        },
        {
            "firstName": "Mikias",
            "lastName": "Alemayehu",
            "fullName": "Mikias Alemayehu",
            "language": "Amharic",
            "gender": "Male",
            "firstNameNative": "ሚኪያስ",
            "lastNameNative": "አለማየሁ",
            "fullNameNative": "ሚኪያስ አለማየሁ"
        },
        {
            "firstName": "Hana'i",
            "lastName": "Sharbatly",
            "fullName": "Hana'i Sharbatly",
            "language": "Arabic",
            "gender": "Female",
            "firstNameNative": "هناء",
            "lastNameNative": "شرباتلي",
            "fullNameNative": "هناء شرباتلي"
        },
        {
            "firstName": "Anisa",
            "lastName": "Meta",
            "fullName": "Anisa Meta",
            "language": "Albanian",
            "gender": "Female",
            "firstNameNative": "Anisa",
            "lastNameNative": "Meta",
            "fullNameNative": "Anisa Meta"
        },
        {
            "firstName": "Koos",
            "lastName": "Kriel",
            "fullName": "Koos Kriel",
            "language": "Afrikaans",
            "gender": "Male",
            "firstNameNative": "Koos",
            "lastNameNative": "Kriel",
            "fullNameNative": "Koos Kriel"
        },
        {
            "firstName": "Qamar",
            "lastName": "Mounir",
            "fullName": "Qamar Mounir",
            "language": "Arabic",
            "gender": "gender neutral",
            "firstNameNative": "قمر",
            "lastNameNative": "منير",
            "fullNameNative": "قمر منير"
        },
        {
            "firstName": "Albert",
            "lastName": "Eksteen",
            "fullName": "Albert Eksteen",
            "language": "Afrikaans",
            "gender": "Male",
            "firstNameNative": "Albert",
            "lastNameNative": "Eksteen",
            "fullNameNative": "Albert Eksteen"
        },
        {
            "firstName": "Aila",
            "lastName": "Hotaki",
            "fullName": "Aila Hotaki",
            "language": "Arabic",
            "gender": "Female",
            "firstNameNative": "آيلة",
            "lastNameNative": "هوتاكي",
            "fullNameNative": "آيلة هوتاكي"
        },
        {
            "firstName": "Baha",
            "lastName": "Nueimat",
            "fullName": "Baha Nueimat",
            "language": "Arabic",
            "gender": "Male",
            "firstNameNative": "بها",
            "lastNameNative": "نيومت",
            "fullNameNative": "بها نيومت"
        },
        {
            "firstName": "Kadijah",
            "lastName": "Batlouni",
            "fullName": "Kadijah Batlouni",
            "language": "Arabic",
            "gender": "Female",
            "firstNameNative": "خديجة",
            "lastNameNative": "بتلوني",
            "fullNameNative": "خديجة بتلوني"
        },
        {
            "firstName": "Gezahegne",
            "lastName": "Mulugeta",
            "fullName": "Gezahegne Mulugeta",
            "language": "Amharic",
            "gender": "Male",
            "firstNameNative": "ገዛሃኝ",
            "lastNameNative": "ሙሉጌታ",
            "fullNameNative": "ገዛሃኝ ሙሉጌታ"
        },
        {
            "firstName": "Dharef",
            "lastName": "Sayegh",
            "fullName": "Dharef Sayegh",
            "language": "Arabic",
            "gender": "Male",
            "firstNameNative": "ظريف",
            "lastNameNative": "صايغ",
            "fullNameNative": "ظريف صايغ"
        },
        {
            "firstName": "Shams",
            "lastName": "Elmarakshi",
            "fullName": "Shams Elmarakshi",
            "language": "Arabic",
            "gender": "gender neutral",
            "firstNameNative": "شمس",
            "lastNameNative": "المراكشي",
            "fullNameNative": "شمس المراكشي"
        },
        {
            "firstName": "Tiaan",
            "lastName": "Theron",
            "fullName": "Tiaan Theron",
            "language": "Afrikaans",
            "gender": "Male",
            "firstNameNative": "Tiaan",
            "lastNameNative": "Theron",
            "fullNameNative": "Tiaan Theron"
        },
        {
            "firstName": "Irene",
            "lastName": "van der Merwe",
            "fullName": "Irene van der Merwe",
            "language": "Afrikaans",
            "gender": "Female",
            "firstNameNative": "Irene",
            "lastNameNative": "van der Merwe",
            "fullNameNative": "Irene van der Merwe"
        },
        {
            "firstName": "Sama",
            "lastName": "Elnubi",
            "fullName": "Sama Elnubi",
            "language": "Arabic",
            "gender": "Female",
            "firstNameNative": "سما",
            "lastNameNative": "النوبي",
            "fullNameNative": "سما النوبي"
        },
        {
            "firstName": "Hasibah",
            "lastName": "Naser",
            "fullName": "Hasibah Naser",
            "language": "Arabic",
            "gender": "Female",
            "firstNameNative": "حسيبة",
            "lastNameNative": "ناصر",
            "fullNameNative": "حسيبة ناصر"
        },
        {
            "firstName": "Gadi",
            "lastName": "Kuzbari",
            "fullName": "Gadi Kuzbari",
            "language": "Arabic",
            "gender": "Male",
            "firstNameNative": "غدي",
            "lastNameNative": "كزبري",
            "fullNameNative": "غدي كزبري"
        },
        {
            "firstName": "Ardit",
            "lastName": "Basha",
            "fullName": "Ardit Basha",
            "language": "Albanian",
            "gender": "Male",
            "firstNameNative": "Ardit",
            "lastNameNative": "Basha",
            "fullNameNative": "Ardit Basha"
        },
        {
            "firstName": "Selhadin",
            "lastName": "Jemal",
            "fullName": "Selhadin Jemal",
            "language": "Amharic",
            "gender": "Male",
            "firstNameNative": "ስልሃዲን",
            "lastNameNative": "ጀማል",
            "fullNameNative": "ስልሃዲን ጀማል"
        },
        {
            "firstName": "Maliha",
            "lastName": "Shamoun",
            "fullName": "Maliha Shamoun",
            "language": "Arabic",
            "gender": "Female",
            "firstNameNative": "مليحة",
            "lastNameNative": "شمعون",
            "fullNameNative": "مليحة شمعون"
        },
        {
            "firstName": "Daniel",
            "lastName": "Sebsibe",
            "fullName": "Daniel Sebsibe",
            "language": "Amharic",
            "gender": "Male",
            "firstNameNative": "ዳንኤል",
            "lastNameNative": "ሰብስቤ",
            "fullNameNative": "ዳንኤል ሰብስቤ"
        },
        {
            "firstName": "Amal",
            "lastName": "Skye",
            "fullName": "Amal Skye",
            "language": "Arabic",
            "gender": "gender neutral",
            "firstNameNative": "أمل",
            "lastNameNative": "سكاي",
            "fullNameNative": "أمل سكاي"
        },
        {
            "firstName": "Elona",
            "lastName": "Leka",
            "fullName": "Elona Bregu",
            "language": "Albanian",
            "gender": "Female",
            "firstNameNative": "Elona",
            "lastNameNative": "Bregu",
            "fullNameNative": "Elona Bregu"
        },
        {
            "firstName": "Khayriyah",
            "lastName": "Khouri",
            "fullName": "Khayriyah Khouri",
            "language": "Arabic",
            "gender": "Female",
            "firstNameNative": "خيرية",
            "lastNameNative": "خوري",
            "fullNameNative": "خيرية خوري"
        },
        {
            "firstName": "Ilir",
            "lastName": "Deda",
            "fullName": "Ilir Devolli",
            "language": "Albanian",
            "gender": "Male",
            "firstNameNative": "Ilir",
            "lastNameNative": "Devolli",
            "fullNameNative": "Ilir Devolli"
        },
        {
            "firstName": "Anila",
            "lastName": "Shehu",
            "fullName": "Anila Shkoza",
            "language": "Albanian",
            "gender": "Female",
            "firstNameNative": "Anila",
            "lastNameNative": "Shkoza",
            "fullNameNative": "Anila Shkoza"
        },
        {
            "firstName": "Baraa",
            "lastName": "Mestaghanmi",
            "fullName": "Baraa Mestaghanmi",
            "language": "Arabic",
            "gender": "gender neutral",
            "firstNameNative": "براء",
            "lastNameNative": "مستغانمي",
            "fullNameNative": "براء مستغانمي"
        },
        {
            "firstName": "Hayat",
            "lastName": "Hassen",
            "fullName": "Hayat Hassen",
            "language": "Amharic",
            "gender": "Female",
            "firstNameNative": "ሃያት",
            "lastNameNative": "ሃሰን",
            "fullNameNative": "ሃያት ሃሰን"
        },
        {
            "firstName": "Alban",
            "lastName": "Fusha",
            "fullName": "Alban Fusha",
            "language": "Albanian",
            "gender": "Male",
            "firstNameNative": "Alban",
            "lastNameNative": "Fusha",
            "fullNameNative": "Alban Fusha"
        },
        {
            "firstName": "Fadilah",
            "lastName": "Baz",
            "fullName": "Fadlah Baz",
            "language": "Arabic",
            "gender": "Female",
            "firstNameNative": "فاضلة",
            "lastNameNative": "باز",
            "fullNameNative": "فاضلة باز"
        },
        {
            "firstName": "Gifti",
            "lastName": "Boru",
            "fullName": "Gifti Boru",
            "language": "Amharic",
            "gender": "Female",
            "firstNameNative": "ጊፍቲ",
            "lastNameNative": "ቦሩ",
            "fullNameNative": "ጊፍቲ ቦሩ"
        },
        {
            "firstName": "Lucine",
            "lastName": "Homsi",
            "fullName": "Lucine Homsi",
            "language": "Arabic",
            "gender": "Female",
            "firstNameNative": "لوسين",
            "lastNameNative": "حمصي",
            "fullNameNative": "لوسين حمصي"
        },
        {
            "firstName": "Gentian",
            "lastName": "Pisha",
            "fullName": "Gentian Pisha",
            "language": "Albanian",
            "gender": "Male",
            "firstNameNative": "Gentian",
            "lastNameNative": "Pisha",
            "fullNameNative": "Gentian Pisha"
        },
        {
            "firstName": "Skye",
            "lastName": "Abadi",
            "fullName": "Skye Abadi",
            "language": "Arabic",
            "gender": "Female",
            "firstNameNative": "سكاي",
            "lastNameNative": "عبادي",
            "fullNameNative": "سكاي عبادي"
        },
        {
            "firstName": "Mekdes",
            "lastName": "Solomon",
            "fullName": "Mekdes Solomon",
            "language": "Amharic",
            "gender": "Female",
            "firstNameNative": "መቅደስ",
            "lastNameNative": "ሰለሞን",
            "fullNameNative": "መቅደስ ሰለሞን"
        },
        {
            "firstName": "Ataa",
            "lastName": "Badakhshi",
            "fullName": "Ataa Badakhshi",
            "language": "Arabic",
            "gender": "Male",
            "firstNameNative": "عطاء",
            "lastNameNative": "بدخشي",
            "fullNameNative": "عطاء بدخشي"
        },
        {
            "firstName": "Abdul-Wahhab",
            "lastName": "Maloof",
            "fullName": "Abdul-Wahhab Maloof",
            "language": "Arabic",
            "gender": "Male",
            "firstNameNative": "عبد الوهاب",
            "lastNameNative": "معلوف",
            "fullNameNative": "عبد الوهاب معلوف"
        },
        {
            "firstName": "Gehad",
            "lastName": "Kerazi",
            "fullName": "Gehad Kerazi",
            "language": "Arabic",
            "gender": "gender neutral",
            "firstNameNative": "جهاد",
            "lastNameNative": "كرازي",
            "fullNameNative": "جهاد كرازي"
        },
        {
            "firstName": "Dritan",
            "lastName": "Kodra",
            "fullName": "Dritan Kodra",
            "language": "Albanian",
            "gender": "Male",
            "firstNameNative": "Dritan",
            "lastNameNative": "Kodra",
            "fullNameNative": "Dritan Kodra"
        },
        {
            "firstName": "Ben",
            "lastName": "van Zyl",
            "fullName": "Ben van Zyl",
            "language": "Afrikaans",
            "gender": "Male",
            "firstNameNative": "Ben",
            "lastNameNative": "van Zyl",
            "fullNameNative": "Ben van Zyl"
        },
        {
            "firstName": "Reda",
            "lastName": "Sayegh",
            "fullName": "Reda Sayegh",
            "language": "Arabic",
            "gender": "gender neutral",
            "firstNameNative": "رضا",
            "lastNameNative": "صايغ",
            "fullNameNative": "رضا صايغ"
        },
        {
            "firstName": "Hafsa",
            "lastName": "Hayek",
            "fullName": "Hafsa Hayek",
            "language": "Arabic",
            "gender": "Female",
            "firstNameNative": "حافصة",
            "lastNameNative": "حايك",
            "fullNameNative": "حافصة حايك"
        },
        {
            "firstName": "Estie",
            "lastName": "Liebenberg",
            "fullName": "Estie Liebenberg",
            "language": "Afrikaans",
            "gender": "Female",
            "firstNameNative": "Estie",
            "lastNameNative": "Liebenberg",
            "fullNameNative": "Estie Liebenberg"
        },
        {
            "firstName": "Ward",
            "lastName": "Refai",
            "fullName": "Ward Refai",
            "language": "Arabic",
            "gender": "gender neutral",
            "firstNameNative": "ورد",
            "lastNameNative": "رفاعي",
            "fullNameNative": "ورد رفاعي"
        },
        {
            "firstName": "Fatos",
            "lastName": "Zeneli",
            "fullName": "Fatos Zeneli",
            "language": "Albanian",
            "gender": "Male",
            "firstNameNative": "Fatos",
            "lastNameNative": "Zeneli",
            "fullNameNative": "Fatos Zeneli"
        },
        {
            "firstName": "Aisha",
            "lastName": "Al-Lami",
            "fullName": "Aisha Al-Lami",
            "language": "Arabic",
            "gender": "Female",
            "firstNameNative": "عائشة",
            "lastNameNative": "اللامي",
            "fullNameNative": "عائشة اللامي"
        },
        {
            "firstName": "Altin",
            "lastName": "Mali",
            "fullName": "Altin Mali",
            "language": "Albanian",
            "gender": "Male",
            "firstNameNative": "Altin",
            "lastNameNative": "Mali",
            "fullNameNative": "Altin Mali"
        },
        {
            "firstName": "Dameer",
            "lastName": "Refai",
            "fullName": "Dameer Refai",
            "language": "Arabic",
            "gender": "Male",
            "firstNameNative": "ضمير",
            "lastNameNative": "رفاعي",
            "fullNameNative": "ضمير رفاعي"
        },
        {
            "firstName": "Lisha",
            "lastName": "Daher",
            "fullName": "Lisha Daher",
            "language": "Arabic",
            "gender": "Female",
            "firstNameNative": "ليشا",
            "lastNameNative": "ضاهر",
            "fullNameNative": "ليشا ضاهر"
        },
        {
            "firstName": "Christelle",
            "lastName": "van Zyl",
            "fullName": "Christelle van Zyl",
            "language": "Afrikaans",
            "gender": "Female",
            "firstNameNative": "Christelle",
            "lastNameNative": "van Zyl",
            "fullNameNative": "Christelle van Zyl"
        },
        {
            "firstName": "Shams Miseidani",
            "lastName": "Shams",
            "fullName": "Miseidani",
            "language": "Arabic",
            "gender": "gender neutral",
            "firstNameNative": "شمس",
            "lastNameNative": "مسعداني",
            "fullNameNative": "شمس مسعداني"
        },
        {
            "firstName": "Alea",
            "lastName": "Natsheh",
            "fullName": "Alea Natsheh",
            "language": "Arabic",
            "gender": "Female",
            "firstNameNative": "علياء",
            "lastNameNative": "ناتشي",
            "fullNameNative": "علياء ناتشي"
        },
        {
            "firstName": "Tekola",
            "lastName": "Melaku",
            "fullName": "Tekola Melaku",
            "language": "Amharic",
            "gender": "Male",
            "firstNameNative": "ተኮላ",
            "lastNameNative": "መላኩ",
            "fullNameNative": "ተኮላ መላኩ"
        },
        {
            "firstName": "Meseret",
            "lastName": "Meles",
            "fullName": "Meseret Meles",
            "language": "Amharic",
            "gender": "Female",
            "firstNameNative": "መሰረት",
            "lastNameNative": "መለስ",
            "fullNameNative": "መሰረት መለስ"
        },
        {
            "firstName": "Ayantu",
            "lastName": "Gemechu",
            "fullName": "Ayantu Gemechu",
            "language": "Amharic",
            "gender": "Female",
            "firstNameNative": "አያንቱ",
            "lastNameNative": "ገመቹ",
            "fullNameNative": "አያንቱ ገመቹ"
        },
        {
            "firstName": "Dirk",
            "lastName": "Fourie",
            "fullName": "Dirk Fourie",
            "language": "Afrikaans",
            "gender": "Male",
            "firstNameNative": "Dirk",
            "lastNameNative": "Fourie",
            "fullNameNative": "Dirk Fourie"
        },
        {
            "firstName": "Siham",
            "lastName": "Izza",
            "fullName": "Siham Izza",
            "language": "Arabic",
            "gender": "Female",
            "firstNameNative": "سهام",
            "lastNameNative": "عزة",
            "fullNameNative": "سهام عزة"
        },
        {
            "firstName": "Fatmir",
            "lastName": "Bregu",
            "fullName": "Fatmir Selvia",
            "language": "Albanian",
            "gender": "Male",
            "firstNameNative": "Fatmir",
            "lastNameNative": "Selvia",
            "fullNameNative": "Fatmir Selvia"
        },
        {
            "firstName": "Blerina",
            "lastName": "Hafizi",
            "fullName": "Blerina Hafizi",
            "language": "Albanian",
            "gender": "Female",
            "firstNameNative": "Blerina",
            "lastNameNative": "Hafizi",
            "fullNameNative": "Blerina Hafizi"
        },
        {
            "firstName": "Ameha",
            "lastName": "Mebratu",
            "fullName": "Ameha Mebratu",
            "language": "Amharic",
            "gender": "Male",
            "firstNameNative": "አመሃ",
            "lastNameNative": "መብራቱ",
            "fullNameNative": "አመሃ መብራቱ"
        },
        {
            "firstName": "Daleen",
            "lastName": "du Plessis",
            "fullName": "Daleen du Plessis",
            "language": "Afrikaans",
            "gender": "Female",
            "firstNameNative": "Daleen",
            "lastNameNative": "du Plessis",
            "fullNameNative": "Daleen du Plessis"
        },
        {
            "firstName": "Hassen",
            "lastName": "Seid",
            "fullName": "Hassen Seid",
            "language": "Amharic",
            "gender": "Male",
            "firstNameNative": "ሃሰን",
            "lastNameNative": "ሰይድ",
            "fullNameNative": "ሃሰን ሰይድ"
        },
        {
            "firstName": "Ermal",
            "lastName": "Prifti",
            "fullName": "Ermal Prifti",
            "language": "Albanian",
            "gender": "Male",
            "firstNameNative": "Ermal",
            "lastNameNative": "Prifti",
            "fullNameNative": "Ermal Prifti"
        },
        {
            "firstName": "Louis",
            "lastName": "de Wet",
            "fullName": "Louis de Wet",
            "language": "Afrikaans",
            "gender": "Male",
            "firstNameNative": "Louis",
            "lastNameNative": "de Wet",
            "fullNameNative": "Louis de Wet"
        },
        {
            "firstName": "Radi",
            "lastName": "Bettar",
            "fullName": "Radi Bettar",
            "language": "Arabic",
            "gender": "Male",
            "firstNameNative": "راضي",
            "lastNameNative": "بيطار",
            "fullNameNative": "راضي بيطار"
        },
        {
            "firstName": "Wesam",
            "lastName": "Baraa",
            "fullName": "Wesam Baraa",
            "language": "Arabic",
            "gender": "gender neutral",
            "firstNameNative": "وسام",
            "lastNameNative": "براء",
            "fullNameNative": "وسام براء"
        }
    ]
}